Workbook

Sheet Summary
A1: FactoryGrid delivery tracker
A2: Two developers in parallel: one backend, one frontend. Built from the FactoryGrid Backend Plan and Frontend Plan (10 Oct 2026). Master plan: FactoryGrid Development Plan (Node.js).
A3: How to use: update the yellow Status cells on Tasks, Hand-offs and Open questions. Everything on this sheet recalculates.
A5: Key dates | C5: Days left
A6: Development starts | B6: 46307 | C6: =B6-TODAY() -> 2
A7: Code freeze | B7: 46401 | C7: =B7-TODAY() -> 96
A8: Beta opens | B8: 46402 | C8: =B8-TODAY() -> 97
A9: Go/no-go | B9: 46414 | C9: =B9-TODAY() -> 109
A10: Production go-live | B10: 46415 | C10: =B10-TODAY() -> 110
A11: Final delivery | B11: 46417 | C11: =B11-TODAY() -> 112
A13: Progress
A14: Owner | B14: Total tasks | C14: Done | D14: In progress | E14: Blocked | F14: Not started | G14: % done | H14: Overdue (not done, past due)
A15: Backend | B15: =COUNTIF(Tasks!$C$2:$C$117,A15) -> 59 | C15: =COUNTIFS(Tasks!$C$2:$C$117,$A15,Tasks!$H$2:$H$117,"Done") -> 0 | D15: =COUNTIFS(Tasks!$C$2:$C$117,$A15,Tasks!$H$2:$H$117,"In progress") -> 0 | E15: =COUNTIFS(Tasks!$C$2:$C$117,$A15,Tasks!$H$2:$H$117,"Blocked") -> 0 | F15: =COUNTIFS(Tasks!$C$2:$C$117,$A15,Tasks!$H$2:$H$117,"Not started") -> 59 | G15: =IF(B15=0,0,C15/B15) -> 0 | H15: =COUNTIFS(Tasks!$C$2:$C$117,$A15,Tasks!$H$2:$H$117,"<>Done",Tasks!$G$2:$G$117,"<"&TODAY()) -> 0
A16: Frontend | B16: =COUNTIF(Tasks!$C$2:$C$117,A16) -> 57 | C16: =COUNTIFS(Tasks!$C$2:$C$117,$A16,Tasks!$H$2:$H$117,"Done") -> 0 | D16: =COUNTIFS(Tasks!$C$2:$C$117,$A16,Tasks!$H$2:$H$117,"In progress") -> 0 | E16: =COUNTIFS(Tasks!$C$2:$C$117,$A16,Tasks!$H$2:$H$117,"Blocked") -> 0 | F16: =COUNTIFS(Tasks!$C$2:$C$117,$A16,Tasks!$H$2:$H$117,"Not started") -> 57 | G16: =IF(B16=0,0,C16/B16) -> 0 | H16: =COUNTIFS(Tasks!$C$2:$C$117,$A16,Tasks!$H$2:$H$117,"<>Done",Tasks!$G$2:$G$117,"<"&TODAY()) -> 0
A17: Total | B17: =SUM(B15:B16) -> 116 | C17: =SUM(C15:C16) -> 0 | D17: =SUM(D15:D16) -> 0 | E17: =SUM(E15:E16) -> 0 | F17: =SUM(F15:F16) -> 116 | G17: =IF(B17=0,0,C17/B17) -> 0 | H17: =SUM(H15:H16) -> 0
A19: Progress by phase
A20: Phase | B20: Start | C20: End | D20: Backend % done | E20: Frontend % done | F20: Exit gates passed
A21: Phase 0 / F0: Foundations | B21: 46307 | C21: 46311 | D21: =IF(COUNTIFS(Tasks!$B$2:$B$117,$A21,Tasks!$C$2:$C$117,"Backend")=0,0,COUNTIFS(Tasks!$B$2:$B$117,$A21,Tasks!$C$2:$C$117,"Backend",Tasks!$H$2:$H$117,"Done")/COUNTIFS(Tasks!$B$2:$B$117,$A21,Tasks!$C$2:$C$117,"Backend")) -> 0 | E21: =IF(COUNTIFS(Tasks!$B$2:$B$117,$A21,Tasks!$C$2:$C$117,"Frontend")=0,0,COUNTIFS(Tasks!$B$2:$B$117,$A21,Tasks!$C$2:$C$117,"Frontend",Tasks!$H$2:$H$117,"Done")/COUNTIFS(Tasks!$B$2:$B$117,$A21,Tasks!$C$2:$C$117,"Frontend")) -> 0 | F21: =COUNTIFS(Tasks!$B$2:$B$117,$A21,Tasks!$D$2:$D$117,"Exit gate",Tasks!$H$2:$H$117,"Done")&" of "&COUNTIFS(Tasks!$B$2:$B$117,$A21,Tasks!$D$2:$D$117,"Exit gate") -> 0 of 2
A22: Phase 1 / F1: Identity | B22: 46314 | C22: 46325 | D22: =IF(COUNTIFS(Tasks!$B$2:$B$117,$A22,Tasks!$C$2:$C$117,"Backend")=0,0,COUNTIFS(Tasks!$B$2:$B$117,$A22,Tasks!$C$2:$C$117,"Backend",Tasks!$H$2:$H$117,"Done")/COUNTIFS(Tasks!$B$2:$B$117,$A22,Tasks!$C$2:$C$117,"Backend")) -> 0 | E22: =IF(COUNTIFS(Tasks!$B$2:$B$117,$A22,Tasks!$C$2:$C$117,"Frontend")=0,0,COUNTIFS(Tasks!$B$2:$B$117,$A22,Tasks!$C$2:$C$117,"Frontend",Tasks!$H$2:$H$117,"Done")/COUNTIFS(Tasks!$B$2:$B$117,$A22,Tasks!$C$2:$C$117,"Frontend")) -> 0 | F22: =COUNTIFS(Tasks!$B$2:$B$117,$A22,Tasks!$D$2:$D$117,"Exit gate",Tasks!$H$2:$H$117,"Done")&" of "&COUNTIFS(Tasks!$B$2:$B$117,$A22,Tasks!$D$2:$D$117,"Exit gate") -> 0 of 2
A23: Phase 2 / F2: Partners, files, compliance | B23: 46328 | C23: 46346 | D23: =IF(COUNTIFS(Tasks!$B$2:$B$117,$A23,Tasks!$C$2:$C$117,"Backend")=0,0,COUNTIFS(Tasks!$B$2:$B$117,$A23,Tasks!$C$2:$C$117,"Backend",Tasks!$H$2:$H$117,"Done")/COUNTIFS(Tasks!$B$2:$B$117,$A23,Tasks!$C$2:$C$117,"Backend")) -> 0 | E23: =IF(COUNTIFS(Tasks!$B$2:$B$117,$A23,Tasks!$C$2:$C$117,"Frontend")=0,0,COUNTIFS(Tasks!$B$2:$B$117,$A23,Tasks!$C$2:$C$117,"Frontend",Tasks!$H$2:$H$117,"Done")/COUNTIFS(Tasks!$B$2:$B$117,$A23,Tasks!$C$2:$C$117,"Frontend")) -> 0 | F23: =COUNTIFS(Tasks!$B$2:$B$117,$A23,Tasks!$D$2:$D$117,"Exit gate",Tasks!$H$2:$H$117,"Done")&" of "&COUNTIFS(Tasks!$B$2:$B$117,$A23,Tasks!$D$2:$D$117,"Exit gate") -> 0 of 2
A24: Phase 3 / F3: Catalog and pricing | B24: 46349 | C24: 46360 | D24: =IF(COUNTIFS(Tasks!$B$2:$B$117,$A24,Tasks!$C$2:$C$117,"Backend")=0,0,COUNTIFS(Tasks!$B$2:$B$117,$A24,Tasks!$C$2:$C$117,"Backend",Tasks!$H$2:$H$117,"Done")/COUNTIFS(Tasks!$B$2:$B$117,$A24,Tasks!$C$2:$C$117,"Backend")) -> 0 | E24: =IF(COUNTIFS(Tasks!$B$2:$B$117,$A24,Tasks!$C$2:$C$117,"Frontend")=0,0,COUNTIFS(Tasks!$B$2:$B$117,$A24,Tasks!$C$2:$C$117,"Frontend",Tasks!$H$2:$H$117,"Done")/COUNTIFS(Tasks!$B$2:$B$117,$A24,Tasks!$C$2:$C$117,"Frontend")) -> 0 | F24: =COUNTIFS(Tasks!$B$2:$B$117,$A24,Tasks!$D$2:$D$117,"Exit gate",Tasks!$H$2:$H$117,"Done")&" of "&COUNTIFS(Tasks!$B$2:$B$117,$A24,Tasks!$D$2:$D$117,"Exit gate") -> 0 of 2
A25: Phase 4 / F4: Sourcing | B25: 46363 | C25: 46374 | D25: =IF(COUNTIFS(Tasks!$B$2:$B$117,$A25,Tasks!$C$2:$C$117,"Backend")=0,0,COUNTIFS(Tasks!$B$2:$B$117,$A25,Tasks!$C$2:$C$117,"Backend",Tasks!$H$2:$H$117,"Done")/COUNTIFS(Tasks!$B$2:$B$117,$A25,Tasks!$C$2:$C$117,"Backend")) -> 0 | E25: =IF(COUNTIFS(Tasks!$B$2:$B$117,$A25,Tasks!$C$2:$C$117,"Frontend")=0,0,COUNTIFS(Tasks!$B$2:$B$117,$A25,Tasks!$C$2:$C$117,"Frontend",Tasks!$H$2:$H$117,"Done")/COUNTIFS(Tasks!$B$2:$B$117,$A25,Tasks!$C$2:$C$117,"Frontend")) -> 0 | F25: =COUNTIFS(Tasks!$B$2:$B$117,$A25,Tasks!$D$2:$D$117,"Exit gate",Tasks!$H$2:$H$117,"Done")&" of "&COUNTIFS(Tasks!$B$2:$B$117,$A25,Tasks!$D$2:$D$117,"Exit gate") -> 0 of 2
A26: Phase 5 / F5: Orders and payments | B26: 46377 | C26: 46392 | D26: =IF(COUNTIFS(Tasks!$B$2:$B$117,$A26,Tasks!$C$2:$C$117,"Backend")=0,0,COUNTIFS(Tasks!$B$2:$B$117,$A26,Tasks!$C$2:$C$117,"Backend",Tasks!$H$2:$H$117,"Done")/COUNTIFS(Tasks!$B$2:$B$117,$A26,Tasks!$C$2:$C$117,"Backend")) -> 0 | E26: =IF(COUNTIFS(Tasks!$B$2:$B$117,$A26,Tasks!$C$2:$C$117,"Frontend")=0,0,COUNTIFS(Tasks!$B$2:$B$117,$A26,Tasks!$C$2:$C$117,"Frontend",Tasks!$H$2:$H$117,"Done")/COUNTIFS(Tasks!$B$2:$B$117,$A26,Tasks!$C$2:$C$117,"Frontend")) -> 0 | F26: =COUNTIFS(Tasks!$B$2:$B$117,$A26,Tasks!$D$2:$D$117,"Exit gate",Tasks!$H$2:$H$117,"Done")&" of "&COUNTIFS(Tasks!$B$2:$B$117,$A26,Tasks!$D$2:$D$117,"Exit gate") -> 0 of 2
A27: Phase 6 / F6: Logistics, notifications, dashboards | B27: 46393 | C27: 46399 | D27: =IF(COUNTIFS(Tasks!$B$2:$B$117,$A27,Tasks!$C$2:$C$117,"Backend")=0,0,COUNTIFS(Tasks!$B$2:$B$117,$A27,Tasks!$C$2:$C$117,"Backend",Tasks!$H$2:$H$117,"Done")/COUNTIFS(Tasks!$B$2:$B$117,$A27,Tasks!$C$2:$C$117,"Backend")) -> 0 | E27: =IF(COUNTIFS(Tasks!$B$2:$B$117,$A27,Tasks!$C$2:$C$117,"Frontend")=0,0,COUNTIFS(Tasks!$B$2:$B$117,$A27,Tasks!$C$2:$C$117,"Frontend",Tasks!$H$2:$H$117,"Done")/COUNTIFS(Tasks!$B$2:$B$117,$A27,Tasks!$C$2:$C$117,"Frontend")) -> 0 | F27: =COUNTIFS(Tasks!$B$2:$B$117,$A27,Tasks!$D$2:$D$117,"Exit gate",Tasks!$H$2:$H$117,"Done")&" of "&COUNTIFS(Tasks!$B$2:$B$117,$A27,Tasks!$D$2:$D$117,"Exit gate") -> 0 of 2
A28: Hardening and code freeze | B28: 46399 | C28: 46401 | D28: =IF(COUNTIFS(Tasks!$B$2:$B$117,$A28,Tasks!$C$2:$C$117,"Backend")=0,0,COUNTIFS(Tasks!$B$2:$B$117,$A28,Tasks!$C$2:$C$117,"Backend",Tasks!$H$2:$H$117,"Done")/COUNTIFS(Tasks!$B$2:$B$117,$A28,Tasks!$C$2:$C$117,"Backend")) -> 0 | E28: =IF(COUNTIFS(Tasks!$B$2:$B$117,$A28,Tasks!$C$2:$C$117,"Frontend")=0,0,COUNTIFS(Tasks!$B$2:$B$117,$A28,Tasks!$C$2:$C$117,"Frontend",Tasks!$H$2:$H$117,"Done")/COUNTIFS(Tasks!$B$2:$B$117,$A28,Tasks!$C$2:$C$117,"Frontend")) -> 0 | F28: =COUNTIFS(Tasks!$B$2:$B$117,$A28,Tasks!$D$2:$D$117,"Exit gate",Tasks!$H$2:$H$117,"Done")&" of "&COUNTIFS(Tasks!$B$2:$B$117,$A28,Tasks!$D$2:$D$117,"Exit gate") -> 0 of 0
A29: Beta testing and launch | B29: 46402 | C29: 46417 | D29: =IF(COUNTIFS(Tasks!$B$2:$B$117,$A29,Tasks!$C$2:$C$117,"Backend")=0,0,COUNTIFS(Tasks!$B$2:$B$117,$A29,Tasks!$C$2:$C$117,"Backend",Tasks!$H$2:$H$117,"Done")/COUNTIFS(Tasks!$B$2:$B$117,$A29,Tasks!$C$2:$C$117,"Backend")) -> 0 | E29: =IF(COUNTIFS(Tasks!$B$2:$B$117,$A29,Tasks!$C$2:$C$117,"Frontend")=0,0,COUNTIFS(Tasks!$B$2:$B$117,$A29,Tasks!$C$2:$C$117,"Frontend",Tasks!$H$2:$H$117,"Done")/COUNTIFS(Tasks!$B$2:$B$117,$A29,Tasks!$C$2:$C$117,"Frontend")) -> 0 | F29: =COUNTIFS(Tasks!$B$2:$B$117,$A29,Tasks!$D$2:$D$117,"Exit gate",Tasks!$H$2:$H$117,"Done")&" of "&COUNTIFS(Tasks!$B$2:$B$117,$A29,Tasks!$D$2:$D$117,"Exit gate") -> 0 of 0

Sheet Tasks
A1: ID | B1: Phase | C1: Owner | D1: Type | E1: Task | F1: Start | G1: Due | H1: Status | I1: Notes
A2: BE-001 | B2: Phase 0 / F0: Foundations | C2: Backend | D2: Task | E2: pnpm workspace + Nx; backend/apps/factorygrid-api, libs/ for auth, errors, prisma, outbox, testing | F2: 46307 | G2: 46311 | H2: Not started
A3: BE-002 | B3: Phase 0 / F0: Foundations | C3: Backend | D3: Task | E3: API standards doc: /api/v1, ApiResponse / ErrorResponse, paging, Idempotency-Key, UTC dates, money in paise | F3: 46307 | G3: 46311 | H3: Not started
A4: BE-003 | B4: Phase 0 / F0: Foundations | C4: Backend | D4: Task | E4: docker-compose: PostgreSQL 17, Redis, MinIO, Mailpit | F4: 46307 | G4: 46311 | H4: Not started
A5: BE-004 | B5: Phase 0 / F0: Foundations | C5: Backend | D5: Task | E5: GitHub Actions: lint, type-check, Jest, OpenAPI lint, contract test, Docker image | F5: 46307 | G5: 46311 | H5: Not started
A6: BE-005 | B6: Phase 0 / F0: Foundations | C6: Backend | D6: Task | E6: Staging environment with database, Redis, S3 bucket and auto-deploy from main | F6: 46307 | G6: 46311 | H6: Not started
A7: BE-006 | B7: Phase 0 / F0: Foundations | C7: Backend | D7: Task | E7: pino logs with request ID, health endpoint, Swagger at /docs | F7: 46307 | G7: 46311 | H7: Not started
A8: BE-007 | B8: Phase 0 / F0: Foundations | C8: Backend | D8: Hand-off | E8: Write and freeze the Identity contract | F8: 46307 | G8: 46309 | H8: Not started
A9: BE-008 | B9: Phase 0 / F0: Foundations | C9: Backend | D9: Task | E9: Apply for Razorpay live KYC, GST/PAN provider account and email provider (SES or SendGrid) | F9: 46307 | G9: 46311 | H9: Not started
A10: BE-009 | B10: Phase 0 / F0: Foundations | C10: Backend | D10: Exit gate | E10: hello-world module deploys to staging behind JWT auth from CI | F10: 46307 | G10: 46311 | H10: Not started
A11: FE-010 | B11: Phase 0 / F0: Foundations | C11: Frontend | D11: Task | E11: Remove VITE_RAZORPAY_KEY_SECRET and verifyRazorpaySignature from razorpayService.ts, and every provider key from VITE_ variables | F11: 46307 | G11: 46307 | H11: Not started
A12: FE-011 | B12: Phase 0 / F0: Foundations | C12: Frontend | D12: Task | E12: Move frontend/ into the pnpm workspace; import @factorygrid/contracts | F12: 46307 | G12: 46311 | H12: Not started
A13: FE-012 | B13: Phase 0 / F0: Foundations | C13: Frontend | D13: Task | E13: One HTTP layer on openapi-fetch: VITE_API_BASE_URL, bearer token, refresh on 401, request ID header, error toasts from ErrorResponse | F13: 46307 | G13: 46311 | H13: Not started
... A117: FE-116 | B117: Beta testing and launch | C117: Frontend | D117: Task | E117: Handover pack: build/deploy steps, env variables, screen-to-API map, Playwright guide, known issues | F117: 46402 | G117: 46417 | H117: Not started

Sheet Hand-offs
A1: Phase | B1: Contract frozen (mocks start) | C1: Live on staging | D1: Integration day | E1: Days of mock-only build | F1: Contract status | G1: Staging status | H1: Integration status
A2: 1 Identity | B2: 46309 | C2: 46323 | D2: 46325 | E2: =C2-B2 -> 14 | F2: Not started | G2: Not started | H2: Not started
A3: 2 Partners, files, compliance | B3: 46323 | C3: 46344 | D3: 46346 | E3: =C3-B3 -> 21 | F3: Not started | G3: Not started | H3: Not started
A4: 3 Catalog and pricing | B4: 46344 | C4: 46358 | D4: 46360 | E4: =C4-B4 -> 14 | F4: Not started | G4: Not started | H4: Not started
A5: 4 Sourcing (RFQ to quote) | B5: 46358 | C5: 46372 | D5: 46374 | E5: =C5-B5 -> 14 | F5: Not started | G5: Not started | H5: Not started
A6: 5 Orders and payments | B6: 46372 | C6: 46391 | D6: 46392 | E6: =C6-B6 -> 19 | F6: Not started | G6: Not started | H6: Not started
A7: 6 Logistics, notifications, dashboards | B7: 46386 | C7: 46398 | D7: 46399 | E7: =C7-B7 -> 12 | F7: Not started | G7: Not started | H7: Not started
A9: Rules: backend writes contracts/<module>.yaml; frontend reviews within 1 working day; frozen when both approve. Breaking change after freeze needs both sign-offs. Integration day = frontend switches the phase from mock to staging and both run the exit-gate flow.

Sheet Beta & launch
A1: Date | B1: Milestone | C1: Owner
A2: 46401 | B2: Code freeze (end of day) | C2: Both
A3: 46402 | B3: Beta opens: pilot accounts get invites | C3: Both
A4: 46402 | B4: Round 1 starts: testers run the full flow; daily triage at 10:00; fixes deploy daily (to 21 Jan) | C4: Both
A5: 46409 | B5: Round 2 build: all P0 and P1 bugs from round 1 fixed | C5: Both
A6: 46412 | B6: Release candidate; only P0 fixes after this | C6: Both
A7: 46413 | B7: Republic Day, off | C7: -
A8: 46414 | B8: Go/no-go with the product owner | C8: Both
A9: 46415 | B9: Production go-live: Razorpay live keys on, test data cleared | C9: Both
A10: 46416 | B10: Hypercare: watch logs and fix live issues | C10: Both
A11: 46417 | B11: Final delivery: handover and sign-off | C11: Both
A13: Bug severity
A14: Severity | B14: Meaning | C14: Fix by
A15: P0 | B15: Flow blocked, wrong money, data leak, security hole | C15: Same day
A16: P1 | B16: Major feature broken, no workaround | C16: Within 2 working days
A17: P2 | B17: Works with a workaround, visual issues | C17: Before go-live if time allows
A18: P3 | B18: Cosmetic or wish list | C18: Post-launch backlog

Sheet Scope
A1: Area | B1: In beta (30 Jan 2027) | C1: After launch (Feb-Apr 2027)
A2: Identity | B2: IAM ported to Node.js, 8 roles, invites, TOTP 2FA, password reset, email verification | C2: Per-device sessions for mobile
A3: Partners and compliance | B3: Onboarding wizard, profiles, document uploads, GST/PAN check via one provider, manual admin approval, audit log | C3: AI document review, MCA checks, virus scan upgrade
A4: Catalog and pricing | B4: Products, 3-level categories, brands, attributes, UoM, tax, CSV import, price lists, margin rules, platform fees | C4: Provider data feeds
A5: Sourcing | B5: RFQ to accepted quote, rules-based manufacturer matching, quote comparison, customer quotation, QA threads | C5: AI matching model
A6: Orders and payments | B6: Master order, admin approval, sub-order split, production status, proforma and tax invoices (PDF), Razorpay advance and invoice payments, refunds | C6: Daily reconciliation dashboard
A7: Logistics | B7: Shipment created by hand with carrier name and tracking number, status updates, delivery confirmation | C7: Blue Dart and Delhivery APIs, temperature logs
A8: Notifications | B8: Email at each hand-off, in-app notifications over Server-Sent Events | C8: SMS, WhatsApp, push, Factory Buddy conversations
A9: Reporting | B9: One summary dashboard per role, CSV export of orders and invoices | C9: reporting-service, read models, PDF exports
A10: Platform | B10: One NestJS app with module boundaries, BullMQ jobs, staging and production | C10: Kong gateway, RabbitMQ, split into services
A11: Mobile | B11: None | C11: Buyer and Partner apps (master plan M0-M3)

Sheet Risks
A1: Track | B1: Risk | C1: Effect | D1: Mitigation
A2: Backend | B2: One backend developer is a single point of failure | C2: Any sick week slips beta | D2: Contract-first specs and tests document the work; Phase 6 and dashboards are first to trim
A3: Both | B3: Phase 5 lands over Christmas and New Year | C3: Orders and payments run late | D3: Contract frozen 16 Dec so frontend builds on mocks before the break; refunds and overdue jobs last
A4: Backend | B4: Razorpay live KYC, GST provider and email provider take weeks | C4: Go-live blocked on paperwork | D4: Apply in Phase 0; build against sandboxes and fakes
A5: Backend | B5: IAM port changes behaviour | C5: Existing users cannot log in | D5: Same schema and shapes first; Java tests are the acceptance suite
A6: Both | B6: Late contract changes | C6: Frontend rework | D6: Freeze dates; breaking changes need both developers' sign-off
A7: Backend | B7: Money maths with JavaScript floats | C7: Wrong invoice totals | D7: Integer paise, decimal.js, rounding tests
A8: Frontend | B8: 72 screens for one developer | C8: F2 and F5 run long | D8: Split big modules only while touching them; hide out-of-scope screens
A9: Frontend | B9: AppContext (5,507 lines) and mockData.ts (7,132 lines) are tangled | C9: Removing one slice breaks other screens | D9: One domain per phase; delete its slice only after its Playwright flow passes
A10: Frontend | B10: Mocks drift from the real API | C10: Surprises on integration day | D10: Generate MSW handlers from the frozen spec, never by hand
A11: Frontend | B11: Backend slips a staging date | C11: Frontend cannot finish its exit gate | D11: Keep building the next phase on mocks; integrate when staging is up
A12: Frontend | B12: Secrets in the browser bundle today | C12: Razorpay secret exposed | D12: Removed on day 1 of F0

Sheet Open questions
A1: Owner | B1: Question | C1: Status | D1: Decision
A2: Product owner | B2: Confirm the beta scope cuts on the Scope sheet | C2: Open
A3: Product owner | B3: How many pilot buyers and manufacturers, and who recruits them by 8 Jan | C3: Open
A4: Backend | B4: Hosting for the API: managed containers (AWS ECS, Render) or a VM | C4: Open
A5: Backend | B5: Email provider and GST/PAN verification provider | C5: Open
A6: Product owner | B6: Is a third developer or QA available in December if Phase 4 or 5 slips | C6: Open
A7: Frontend | B7: Which out-of-scope screens are hidden and which show Coming soon | C7: Open
A8: Frontend | B8: Bug tracker for beta testers (GitHub Issues, Jira or a form) | C8: Open
A9: Frontend | B9: Browsers and minimum screen width to support at launch | C9: Open
